{
  "824841": {
    "state": "LIVE",
    "matchup": "New York Yankees vs Baltimore Orioles"
  },
  "824438": {
    "state": "LIVE",
    "matchup": "Los Angeles Angels vs Cleveland Guardians"
  },
  "824519": {
    "state": "PREVIEW",
    "matchup": "Washington Nationals vs Cincinnati Reds"
  },
  "823386": {
    "state": "DELAYED",
    "matchup": "Colorado Rockies vs Pittsburgh Pirates"
  },
  "824763": {
    "state": "PREVIEW",
    "matchup": "Philadelphia Phillies vs Boston Red Sox"
  },
  "822815": {
    "state": "PREVIEW",
    "matchup": "Tampa Bay Rays vs Toronto Blue Jays"
  },
  "823631": {
    "state": "PREVIEW",
    "matchup": "Detroit Tigers vs New York Mets"
  },
  "824928": {
    "state": "PREVIEW",
    "matchup": "Chicago Cubs vs Atlanta Braves"
  },
  "824603": {
    "state": "PREVIEW",
    "matchup": "Kansas City Royals vs Chicago White Sox"
  },
  "823710": {
    "state": "PREVIEW",
    "matchup": "Miami Marlins vs Minnesota Twins"
  },
  "823791": {
    "state": "PREVIEW",
    "matchup": "San Diego Padres vs Milwaukee Brewers"
  },
  "822900": {
    "state": "PREVIEW",
    "matchup": "Arizona Diamondbacks vs Texas Rangers"
  },
  "824195": {
    "state": "PREVIEW",
    "matchup": "Seattle Mariners vs Houston Astros"
  },
  "825010": {
    "state": "PREVIEW",
    "matchup": "St. Louis Cardinals vs Athletics"
  },
  "823952": {
    "state": "PREVIEW",
    "matchup": "San Francisco Giants vs Los Angeles Dodgers"
  }
}